SCYN-1.0.6.dist-info/METADATA
SCYN-1.0.6.dist-info/RECORD
SCYN-1.0.6.dist-info/WHEEL
SCYN-1.0.6.dist-info/top_level.txt
scyn/__init__.py
scyn/scyn.py
scyn/utils.py
scyn/version.py
