Metadata-Version: 2.1
Name: SCYN
Version: 1.0.6
Summary: SCYN: Single cell CNV profiling method using dynamic programming
Home-page: https://github.com/xikanfeng2/SCYN
Author: Xikang Feng
Author-email: xikanfeng2@gmail.com
License: UNKNOWN
Platform: UNKNOWN
Classifier: Programming Language :: Python :: 3
Classifier: License :: OSI Approved :: MIT License
Classifier: Operating System :: OS Independent
